{
  "version": "v76-world-release-autonomous",
  "release": "World Release Autonomous Command",
  "root_html_pages": 62,
  "published_html_pages_including_resources": 69,
  "root_html_page_files": [
    "agialpha-ledger-route.html",
    "ascension.html",
    "autopilot-mission-builder.html",
    "biography.html",
    "developers.html",
    "evidence-docket.html",
    "execution-moat.html",
    "executive-brief.html",
    "how-it-works.html",
    "index.html",
    "jobs.html",
    "mission-os-paper.html",
    "mission-os.html",
    "personal-proof-sprint.html",
    "pilot-guide.html",
    "proof-card-001.html",
    "proof-card-002.html",
    "proof-card-003.html",
    "proof-card-004.html",
    "proof-card-005.html",
    "proof-card-006.html",
    "proof-card-007.html",
    "proof-card-008.html",
    "proof-card-009.html",
    "proof-card-010.html",
    "proof-card-011.html",
    "proof-card-012.html",
    "proof-card-013.html",
    "proof-card-014.html",
    "proof-card-015.html",
    "proof-card-016.html",
    "proof-card-017.html",
    "proof-card-018.html",
    "proof-card-019.html",
    "proof-card-020.html",
    "proof-card-021.html",
    "proof-card-022.html",
    "proof-card-023.html",
    "proof-card-024.html",
    "proof-card-025.html",
    "proof-card-026.html",
    "proof-card-027.html",
    "proof-card-028.html",
    "proof-card-029.html",
    "proof-card-030.html",
    "proof-card-031.html",
    "proof-cards.html",
    "proof-observatory.html",
    "proof-sprint-builder.html",
    "proof-treasury-simulation-003.html",
    "proof-treasury-simulation-004.html",
    "proof-treasury-simulation-005.html",
    "proof-treasury.html",
    "regular-person.html",
    "research.html",
    "resources.html",
    "roadmap.html",
    "sovereign-rsi-control-plane.html",
    "start-here.html",
    "system-map.html",
    "use-cases.html",
    "whitepaper.html"
  ],
  "published_html_page_files": [
    "agialpha-ledger-route.html",
    "ascension.html",
    "autopilot-mission-builder.html",
    "biography.html",
    "developers.html",
    "downloads/GoalOS_Personal_Proof_Sprint_Builder_v3.html",
    "downloads/proof-treasury-simulation-003/simulation-preview-index.html",
    "downloads/proof-treasury-simulation-004/index.html",
    "evidence-docket.html",
    "execution-moat.html",
    "executive-brief.html",
    "how-it-works.html",
    "index.html",
    "jobs.html",
    "mission-os-paper.html",
    "mission-os.html",
    "personal-proof-sprint.html",
    "pilot-guide.html",
    "proof-card-001.html",
    "proof-card-002.html",
    "proof-card-003.html",
    "proof-card-004.html",
    "proof-card-005.html",
    "proof-card-006.html",
    "proof-card-007.html",
    "proof-card-008.html",
    "proof-card-009.html",
    "proof-card-010.html",
    "proof-card-011.html",
    "proof-card-012.html",
    "proof-card-013.html",
    "proof-card-014.html",
    "proof-card-015.html",
    "proof-card-016.html",
    "proof-card-017.html",
    "proof-card-018.html",
    "proof-card-019.html",
    "proof-card-020.html",
    "proof-card-021.html",
    "proof-card-022.html",
    "proof-card-023.html",
    "proof-card-024.html",
    "proof-card-025.html",
    "proof-card-026.html",
    "proof-card-027.html",
    "proof-card-028.html",
    "proof-card-029.html",
    "proof-card-030.html",
    "proof-card-031.html",
    "proof-cards.html",
    "proof-observatory.html",
    "proof-sprint-builder.html",
    "proof-treasury-simulation-003.html",
    "proof-treasury-simulation-004.html",
    "proof-treasury-simulation-005.html",
    "proof-treasury.html",
    "regular-person.html",
    "research.html",
    "resources.html",
    "resources/GoalOS_Personal_Proof_Sprint_Builder_v3.html",
    "resources/autopilot/interactive/07_AGIALPHA_Autopilot_Mission_Builder_v2.html",
    "resources/mission-os/example-output/index.html",
    "resources/mission-os/web/GoalOS_Mission_OS_Landing_Page_v12.html",
    "roadmap.html",
    "sovereign-rsi-control-plane.html",
    "start-here.html",
    "system-map.html",
    "use-cases.html",
    "whitepaper.html"
  ],
  "checks": {
    "v74_v75_visual_continuity_retained": true,
    "autonomous_github_action_included": true,
    "proof_card_028_reformulated": true,
    "legacy_superintelligent_machine_quote_removed_from_public_site": true,
    "claim_boundary": "strict",
    "public_alpha_boundary": true,
    "zip_files_blocked_from_public_artifact": true,
    "build_script_passed": true,
    "verify_script_passed": true,
    "js_syntax_check_passed": true
  },
  "workflow": ".github/workflows/goalos-agialpha-ascension-autonomous-world-release.yml",
  "build_script": "scripts/build_goalos_agialpha_ascension_website_v76_world_release.py",
  "verify_script": "scripts/verify_goalos_agialpha_ascension_website_v76_world_release.py"
}
